AUTHORS
CHANGES
LICENSE
MANIFEST.in
README.md
requirements-doc.txt
requirements-full.txt
requirements-github.txt
requirements-rtd.txt
setup.py
docs/Makefile
docs/about.rst
docs/agreement.rst
docs/bugs.rst
docs/community.rst
docs/conf.py
docs/contributing-core.rst
docs/contributing-drivers.rst
docs/contributing.rst
docs/driversdoc.py
docs/extract_snippets.py
docs/faq.rst
docs/index.rst
docs/make.bat
docs/overview.rst
docs/_static/lantz_logo.png
docs/_static/ui-fungen.png
docs/_static/blocks/chart.png
docs/_static/blocks/loop.png
docs/_static/blocks/scan.png
docs/_static/blocks/scanfeat.png
docs/_static/guides/git1.png
docs/_static/guides/git2.png
docs/_static/guides/scanfrequency.png
docs/_static/guides/scanfrequency.ui
docs/_static/guides/ui-driver-1.png
docs/_static/guides/ui-feat-two-widgets-1.png
docs/_static/guides/ui-initializing-1.png
docs/_static/guides/ui-initializing-mov.gif
docs/_static/guides/ui-two-drivers-1.png
docs/_static/tutorial/fungen.ui
docs/_static/tutorial/gui-app.png
docs/_static/tutorial/rich-gui-app.png
docs/_templates/sidebarintro.html
docs/_templates/sidebarlogo.html
docs/_themes/.gitignore
docs/_themes/LICENSE
docs/_themes/README
docs/_themes/flask_theme_support.py
docs/_themes/lantz/layout.html
docs/_themes/lantz/theme.conf
docs/_themes/lantz/static/basic.css
docs/_themes/lantz/static/default.css
docs/_themes/lantz/static/default2.css
docs/_themes/lantz/static/doctools.js
docs/_themes/lantz/static/lantz16.png
docs/_themes/lantz/static/lantz16.psd
docs/_themes/lantz/static/py.png
docs/_themes/lantz/static/sidebar.js
docs/api/general.rst
docs/api/index.rst
docs/api/interfaces.rst
docs/api/processors.rst
docs/api/stats.rst
docs/api/stringparser.rst
docs/api/support.rst
docs/api/ui.rst
docs/guides/blocks.rst
docs/guides/build-backend.rst
docs/guides/build-frontend.rst
docs/guides/defaults.rst
docs/guides/index.rst
docs/guides/initializing-setup.rst
docs/guides/new-driver.rst
docs/guides/ui-driver.rst
docs/guides/ui-feat-two-widgets.rst
lantzdev.egg-info/PKG-INFO
lantzdev.egg-info/SOURCES.txt
lantzdev.egg-info/dependency_links.txt
lantzdev.egg-info/entry_points.txt
lantzdev.egg-info/not-zip-safe
lantzdev.egg-info/requires.txt
lantzdev.egg-info/top_level.txt